[{"__symbolic":"module","version":4,"metadata":{"Flattener":{"__symbolic":"class","extends":{"__symbolic":"reference","module":"./type","name":"Base","line":15,"character":31},"members":{"__ctor__":[{"__symbolic":"constructor"}]},"statics":{"$t":{"__symbolic":"call","expression":{"__symbolic":"reference","module":"./type","name":"markType","line":16,"character":19},"arguments":[{"__symbolic":"reference","name":"Flattener"},"Flattener"]},"c":{"__symbolic":"function","parameters":["a","b","c","d","e","f"],"value":{"__symbolic":"call","expression":{"__symbolic":"select","expression":{"__symbolic":"reference","name":"Flattener"},"member":"b"},"arguments":[{"__symbolic":"reference","name":"a"},{"__symbolic":"error","message":"Lambda not supported","line":26,"character":24},{"__symbolic":"reference","name":"b"},{"__symbolic":"reference","name":"c"},{"__symbolic":"reference","name":"d"},{"__symbolic":"reference","name":"e"},{"__symbolic":"reference","name":"f"}]}},"a":{"__symbolic":"function","parameters":["a","b","c","d","e","f","g"],"value":{"__symbolic":"call","expression":{"__symbolic":"select","expression":{"__symbolic":"reference","name":"Flattener"},"member":"b"},"arguments":[{"__symbolic":"reference","name":"a"},{"__symbolic":"error","message":"Lambda not supported","line":29,"character":24},{"__symbolic":"reference","name":"c"},{"__symbolic":"reference","name":"d"},{"__symbolic":"reference","name":"e"},{"__symbolic":"reference","name":"f"},{"__symbolic":"reference","name":"g"}]}}}}}}]