[{"__symbolic":"module","version":4,"metadata":{"FormatCellsDialogBorderInfo":{"__symbolic":"class","extends":{"__symbolic":"reference","module":"../../igniteui-angular-core/ES2015/type","name":"Base","line":13,"character":49},"members":{"__ctor__":[{"__symbolic":"constructor","parameters":[{"__symbolic":"reference","name":"boolean"},{"__symbolic":"reference","name":"boolean"}]}],"_bs":[{"__symbolic":"method"}],"_br":[{"__symbolic":"method"}]},"statics":{"$t":{"__symbolic":"call","expression":{"__symbolic":"reference","module":"../../igniteui-angular-core/ES2015/type","name":"markType","line":14,"character":19},"arguments":[{"__symbolic":"reference","name":"FormatCellsDialogBorderInfo"},"FormatCellsDialogBorderInfo",{"__symbolic":"select","expression":{"__symbolic":"reference","module":"../../igniteui-angular-core/ES2015/type","name":"Base","line":14,"character":94},"member":"$"},[{"__symbolic":"reference","module":"../../igniteui-angular-core/ES2015/type","name":"INotifyPropertyChanged_$type","line":14,"character":104}]]},"_aq":{"__symbolic":"function","parameters":["a"],"value":{"__symbolic":"binop","operator":"||","left":{"__symbolic":"binop","operator":"==","left":{"__symbolic":"reference","name":"a"},"right":0},"right":{"__symbolic":"binop","operator":"==","left":{"__symbolic":"reference","name":"a"},"right":-1}}}}}}}]